Dosepy/__init__.py
Dosepy/app.py
Dosepy/calibration.py
Dosepy/i_o.py
Dosepy/image.py
Dosepy/rtdose.py
Dosepy/tiff2dose.py
Dosepy/Icon/Icon.png
Dosepy/Icon/LogoDosepy.png
Dosepy/Icon/Logo_Dosepy.png
Dosepy/Icon/cut-regular-60.png
Dosepy/Icon/cut_icon.png
Dosepy/Icon/folder.png
Dosepy/Icon/grid-regular-60.png
Dosepy/Icon/reflect-horizontal-regular-60.png
Dosepy/Icon/reflect-vertical-regular-60.png
Dosepy/Icon/rotate-left-regular-60.png
Dosepy/Icon/rotate-right-regular-60.png
Dosepy/Icon/save.png
Dosepy/Icon/selection-regular-60.png
Dosepy/app_components/__init__.py
Dosepy/app_components/about_window.py
Dosepy/app_components/calibration_widget.py
Dosepy/app_components/config_window.py
Dosepy/app_components/ct_viewer.py
Dosepy/app_components/file_dialog.py
Dosepy/app_components/licencia_window.py
Dosepy/app_components/main_window.py
Dosepy/app_components/tif_widget.py
Dosepy/app_components/tiff2dose_widget.py
Dosepy/app_components/blitting_examples/__init__.py
Dosepy/app_components/blitting_examples/cross_hair_cursor.py
Dosepy/app_components/blitting_examples/cursor.py
Dosepy/app_components/blitting_examples/dp_multi_cursor.py
Dosepy/app_components/blitting_examples/draggable rectangle.py
Dosepy/app_components/blitting_examples/multi_cursor.py
Dosepy/app_components/blitting_examples/to_do_rendering.py
Dosepy/app_components/styles/styles.py
Dosepy/app_controller/__init__.py
Dosepy/app_controller/app_controller.py
Dosepy/app_model/__init__.py
Dosepy/app_model/app_model.py
Dosepy/config/__init__.py
Dosepy/config/io_settings.py
Dosepy/config/settings.toml
Dosepy/data/D_FILM.csv
Dosepy/data/D_TPS.csv
Dosepy/old/GUI.py
Dosepy/old/__init__.py
Dosepy/old/dose.py
Dosepy/old/gui_components/Bloque_Imagenes.py
Dosepy/old/gui_components/Bloque_gamma.py
Dosepy/old/gui_components/about_window.py
Dosepy/old/gui_components/film_to_doseGUI.py
Dosepy/old/gui_components/licencia_window.py
Dosepy/tools/__init__.py
Dosepy/tools/array_utils.py
Dosepy/tools/equate.py
dosepy-0.12.2.dist-info/licenses/LICENSE
dosepy-0.12.2.dist-info/METADATA
dosepy-0.12.2.dist-info/WHEEL
dosepy-0.12.2.dist-info/top_level.txt
dosepy-0.12.2.dist-info/RECORD
