Metadata-Version: 2.4
Name: Dosepy
Version: 0.12.2
Summary: Film dosimetry and gamma analysis for dose distributions in radiotherapy
Author-email: Luis Alfonso Olivares Jimenez <alfonso.cucei.udg@gmail.com>
Project-URL: homepage, https://dosepy.readthedocs.io/en/latest/intro.html
Project-URL: repository, https://pypi.org/project/Dosepy/
Project-URL: Bug-Tracker, https://github.com/LuisOlivaresJ/Dosepy
Keywords: Radiotherapy,Dose distribution,gamma index,python
Classifier: Programming Language :: Python :: 3
Classifier: Operating System :: OS Independent
Classifier: Intended Audience :: Science/Research
Classifier: Intended Audience :: Education
Classifier: Intended Audience :: Healthcare Industry
Classifier: Topic :: Scientific/Engineering :: Medical Science Apps.
Classifier: Topic :: Scientific/Engineering :: Physics
Classifier: Natural Language :: Spanish
Requires-Python: >=3.11
License-File: LICENSE
Requires-Dist: imageio>=2.35.1
Requires-Dist: numpy>=2.1.1
Requires-Dist: matplotlib>=3.9.2
Requires-Dist: tifffile>=2024.09.20
Requires-Dist: scipy>=1.14.1
Requires-Dist: pydantic>=2.9.2
Requires-Dist: pydicom>=3.0.1
Requires-Dist: scikit-image>=0.25.0
Requires-Dist: tomlkit>=0.13.2
Requires-Dist: tqdm>=4.66.5
Requires-Dist: pyyaml>=6.0.2
Requires-Dist: pytest>=8.3.5
Requires-Dist: pip>=25.0.1
Requires-Dist: plotly>=6.0.1
Requires-Dist: nbformat>=5.10.4
Requires-Dist: simpleitk>=2.5.2
Requires-Dist: gdown>=5.2.0
Requires-Dist: pytest-cov>=6.2.1
Dynamic: license-file
